esphome_dashboard_api/__init__.py
esphome_dashboard_api/py.typed
esphome_dashboard_api-1.3.0.dist-info/licenses/LICENSE
esphome_dashboard_api-1.3.0.dist-info/METADATA
esphome_dashboard_api-1.3.0.dist-info/WHEEL
esphome_dashboard_api-1.3.0.dist-info/top_level.txt
esphome_dashboard_api-1.3.0.dist-info/zip-safe
esphome_dashboard_api-1.3.0.dist-info/RECORD
