Metadata-Version: 2.4
Name: esphome-dashboard-api
Version: 1.3.0
Summary: API to interact with ESPHome Dashboard
Author-email: ESPHome <esphome@nabucasa.com>
License: MIT
Project-URL: Homepage, https://github.com/esphome/dashboard-api
Platform: any
Requires-Python: >=3.4.0
License-File: LICENSE
Requires-Dist: aiohttp
Requires-Dist: orjson
Dynamic: license-file
